galene_stream/__init__.py
galene_stream/__main__.py
galene_stream/cli.py
galene_stream/galene.py
galene_stream/version.py
galene_stream/webrtc.py
tests/__init__.py
tests/test_webrtc.py
galene_stream-0.2.0.dist-info/CC0-1.0.txt
galene_stream-0.2.0.dist-info/METADATA
galene_stream-0.2.0.dist-info/MIT.txt
galene_stream-0.2.0.dist-info/WHEEL
galene_stream-0.2.0.dist-info/entry_points.txt
galene_stream-0.2.0.dist-info/top_level.txt
galene_stream-0.2.0.dist-info/RECORD
