Metadata-Version: 2.1
Name: galene-stream
Version: 0.2.0
Summary: Gateway to send streams to Galène videoconference server.
Home-page: https://github.com/erdnaxe/galene-stream
Maintainer: erdnaxe
Maintainer-email: erdnaxe@crans.org
License: MIT
Keywords: galene,stream,rtmp,srt,webrtc,gstreamer
Classifier: Development Status :: 4 - Beta
Classifier: Environment :: Console
Classifier: Intended Audience :: Developers
Classifier: Intended Audience :: Information Technology
Classifier: License :: OSI Approved :: MIT License
Classifier: Operating System :: OS Independent
Classifier: Programming Language :: Python :: 3.8
Classifier: Programming Language :: Python :: 3.9
Classifier: Programming Language :: Python :: 3.10
Classifier: Programming Language :: Python :: 3.11
License-File: LICENSES/MIT.txt
License-File: LICENSES/CC0-1.0.txt
Requires-Dist: websockets
Requires-Dist: PyGObject
